gym_xarm/__init__.py
gym_xarm/tasks/__init__.py
gym_xarm/tasks/assets/lift.xml
gym_xarm/tasks/assets/mesh/base_link.stl
gym_xarm/tasks/assets/mesh/block_inner.stl
gym_xarm/tasks/assets/mesh/block_inner2.stl
gym_xarm/tasks/assets/mesh/block_outer.stl
gym_xarm/tasks/assets/mesh/left_finger.stl
gym_xarm/tasks/assets/mesh/left_inner_knuckle.stl
gym_xarm/tasks/assets/mesh/left_outer_knuckle.stl
gym_xarm/tasks/assets/mesh/link1.stl
gym_xarm/tasks/assets/mesh/link2.stl
gym_xarm/tasks/assets/mesh/link3.stl
gym_xarm/tasks/assets/mesh/link4.stl
gym_xarm/tasks/assets/mesh/link5.stl
gym_xarm/tasks/assets/mesh/link6.stl
gym_xarm/tasks/assets/mesh/link7.stl
gym_xarm/tasks/assets/mesh/link_base.stl
gym_xarm/tasks/assets/mesh/right_finger.stl
gym_xarm/tasks/assets/mesh/right_inner_knuckle.stl
gym_xarm/tasks/assets/mesh/right_outer_knuckle.stl
gym_xarm/tasks/assets/peg_in_box.xml
gym_xarm/tasks/assets/push.xml
gym_xarm/tasks/assets/reach.xml
gym_xarm/tasks/assets/shared.xml
gym_xarm/tasks/assets/xarm.xml
gym_xarm/tasks/base.py
gym_xarm/tasks/lift.py
gym_xarm/tasks/mocap.py
gym_xarm/tasks/peg_in_box.py
gym_xarm/tasks/push.py
gym_xarm/tasks/reach.py
gym_xarm-0.1.1.dist-info/LICENSE
gym_xarm-0.1.1.dist-info/METADATA
gym_xarm-0.1.1.dist-info/WHEEL
gym_xarm-0.1.1.dist-info/RECORD
