Metadata-Version: 2.1
Name: gym-xarm
Version: 0.1.1
Summary: A gym environment for xArm
License: Apache-2.0
Keywords: robotics,deep,reinforcement,learning,xarm,environment,gym,gymnasium,mujoco
Author: Rémi Cadène
Author-email: re.cadene@gmail.com
Requires-Python: >=3.10,<4.0
Classifier: Development Status :: 3 - Alpha
Classifier: Intended Audience :: Developers
Classifier: License :: OSI Approved :: Apache Software License
Classifier: Programming Language :: Python :: 3
Classifier: Programming Language :: Python :: 3.10
Classifier: Programming Language :: Python :: 3.11
Classifier: Programming Language :: Python :: 3.12
Classifier: Topic :: Software Development :: Build Tools
Provides-Extra: dev
Provides-Extra: test
Requires-Dist: debugpy (>=1.8.1) ; extra == "dev"
Requires-Dist: gymnasium (>=0.29.1)
Requires-Dist: gymnasium-robotics (>=1.2.4)
Requires-Dist: mujoco (>=2.3.7,<3.0.0)
Requires-Dist: pre-commit (>=3.7.0) ; extra == "dev"
Requires-Dist: pytest (>=8.1.0) ; extra == "test"
Requires-Dist: pytest-cov (>=5.0.0) ; extra == "test"
